ai_kit_file_management/__init__.py
ai_kit_file_management/admin.py
ai_kit_file_management/apps.py
ai_kit_file_management/managers.py
ai_kit_file_management/models.py
ai_kit_file_management/serializers.py
ai_kit_file_management/settings.py
ai_kit_file_management/urls.py
ai_kit_file_management/views.py
ai_kit_file_management/migrations/0001_initial.py
ai_kit_file_management/migrations/0002_auto_20200630_1447.py
ai_kit_file_management/migrations/__init__.py
ai_kit_file_management/tests/__init__.py
ai_kit_file_management/tests/settings.py
ai_kit_file_management/tests/test_api.py
ai_kit_file_management/tests/test_file_model.py
ai_kit_file_management/tests/test_settings.py
ai_kit_file_management/tests/tests.py
django_ai_kit_file_management-0.2.2.dist-info/METADATA
django_ai_kit_file_management-0.2.2.dist-info/WHEEL
django_ai_kit_file_management-0.2.2.dist-info/top_level.txt
django_ai_kit_file_management-0.2.2.dist-info/RECORD
